pytarallo/AuditEntry.py
pytarallo/Errors.py
pytarallo/Item.py
pytarallo/ItemBase.py
pytarallo/ItemToUpload.py
pytarallo/Product.py
pytarallo/ProductToUpload.py
pytarallo/Tarallo.py
pytarallo/__init__.py
pytarallo-2.4.0.dist-info/LICENSE
pytarallo-2.4.0.dist-info/METADATA
pytarallo-2.4.0.dist-info/WHEEL
pytarallo-2.4.0.dist-info/top_level.txt
pytarallo-2.4.0.dist-info/RECORD
