Metadata-Version: 2.1
Name: pytarallo
Version: 2.4.0
Summary: Python API for the T.A.R.A.L.L.O. Inventory System
Home-page: https://github.com/WEEE-Open/pytarallo
Download-URL: https://github.com/WEEE-Open/pytarallo/archive/2.4.0.tar.gz
Author: Various people
Author-email: weeeopen@polito.it
License: MIT
Keywords: WEEEOpen,python-tarallo,T.A.R.A.L.L.O.,Inventory system
Platform: UNKNOWN
Classifier: Development Status :: 4 - Beta
Classifier: Intended Audience :: Developers
Classifier: Topic :: Software Development :: Build Tools
Classifier: License :: OSI Approved :: MIT License
Classifier: Programming Language :: Python :: 3.6
License-File: LICENSE
Requires-Dist: requests
Provides-Extra: dev
Requires-Dist: nose ; extra == 'dev'
Requires-Dist: python-dotenv ; extra == 'dev'
